pandas_mesh.py
bpy_pandas_mesh-0.1.0.dist-info/LICENSE
bpy_pandas_mesh-0.1.0.dist-info/METADATA
bpy_pandas_mesh-0.1.0.dist-info/WHEEL
bpy_pandas_mesh-0.1.0.dist-info/top_level.txt
bpy_pandas_mesh-0.1.0.dist-info/RECORD
